{
  "$schema": "https://developer.microsoft.com/json-schemas/fabric/item/report/definition/page/2.0.0/schema.json",
  "name": "28986aea68a994571065",
  "displayName": "📊 Global Performance - Free Analysis",
  "displayOption": "FitToPage",
  "height": 720,
  "width": 1280,
  "objects": {
    "background": [
      {
        "properties": {
          "image": {
            "image": {
              "name": {
                "expr": {
                  "Literal": {
                    "Value": "'Historical_performance - Free Analysis.svg'"
                  }
                }
              },
              "url": {
                "expr": {
                  "ResourcePackageItem": {
                    "PackageName": "RegisteredResources",
                    "PackageType": 1,
                    "ItemName": "Historical_performance_-_Free_24928659081304172.svg"
                  }
                }
              },
              "scaling": {
                "expr": {
                  "Literal": {
                    "Value": "'Fit'"
                  }
                }
              }
            }
          }
        }
      }
    ]
  },
  "visibility": "HiddenInViewMode"
}
